peterpy/__init__.py
peterpy/peterpy.py
peterpy-1.1.1.dist-info/LICENSE.txt
peterpy-1.1.1.dist-info/METADATA
peterpy-1.1.1.dist-info/WHEEL
peterpy-1.1.1.dist-info/top_level.txt
peterpy-1.1.1.dist-info/RECORD
